useragent_classifier/__init__.py
useragent_classifier/classifier.py
useragent_classifier/custom_transformers/__init__.py
useragent_classifier/custom_transformers/transformers.py
useragent_classifier/features_importances.py
useragent_classifier/graphical_explanation.py
useragent_classifier/main.py
useragent_classifier-0.8.4.dist-info/entry_points.txt
useragent_classifier-0.8.4.dist-info/WHEEL
useragent_classifier-0.8.4.dist-info/METADATA
useragent_classifier-0.8.4.dist-info/RECORD
