Metadata-Version: 2.1
Name: useragent-classifier
Version: 0.8.4
Summary: 
Keywords: user-agent,classification
Author: thibaultB
Author-email: thibault.blanc@yahoo.fr
Requires-Python: >=3.8,<4.0
Classifier: Programming Language :: Python :: 3
Classifier: Programming Language :: Python :: 3.10
Classifier: Programming Language :: Python :: 3.8
Classifier: Programming Language :: Python :: 3.9
Requires-Dist: click (>=8.0.4,<9.0.0)
Requires-Dist: dash (>=2.3.0,<3.0.0)
Requires-Dist: pandas (>=1.4.1,<2.0.0)
Requires-Dist: plotly (>=5.6.0,<6.0.0)
Requires-Dist: scikit-learn (>=1.0.2,<2.0.0)
